xontrib/prompt_starship.py
xontrib_prompt_starship-0.3.7.dist-info/licenses/LICENSE
xontrib_prompt_starship-0.3.7.dist-info/METADATA
xontrib_prompt_starship-0.3.7.dist-info/WHEEL
xontrib_prompt_starship-0.3.7.dist-info/top_level.txt
xontrib_prompt_starship-0.3.7.dist-info/RECORD
