Metadata-Version: 2.4
Name: xontrib-prompt-starship
Version: 0.3.7
Summary: Starship prompt in xonsh shell.
Home-page: https://github.com/anki-code/xontrib-prompt-starship
Author: anki-code
Author-email: no@no.no
License: MIT
Project-URL: Documentation, https://github.com/anki-code/xontrib-prompt-starship/blob/master/README.md
Project-URL: Code, https://github.com/anki-code/xontrib-prompt-starship
Project-URL: Issue tracker, https://github.com/anki-code/xontrib-prompt-starship/issues
Platform: any
Classifier: Programming Language :: Python :: 3
Classifier: Programming Language :: Python :: 3.6
Classifier: Programming Language :: Python :: 3.7
Classifier: Programming Language :: Python :: 3.8
Classifier: License :: OSI Approved :: MIT License
Classifier: Operating System :: OS Independent
Classifier: Topic :: System :: Shells
Classifier: Topic :: System :: System Shells
Classifier: Topic :: Terminals
Requires-Python: >=3.6
License-File: LICENSE
Requires-Dist: xonsh
Dynamic: author
Dynamic: author-email
Dynamic: classifier
Dynamic: description
Dynamic: description-content-type
Dynamic: home-page
Dynamic: license
Dynamic: license-file
Dynamic: platform
Dynamic: project-url
Dynamic: requires-dist
Dynamic: requires-python
Dynamic: summary
